uyghur/__init__.py
uyghur/conversion.py
uyghur-0.1.2.dist-info/WHEEL
uyghur-0.1.2.dist-info/METADATA
uyghur-0.1.2.dist-info/RECORD
