Metadata-Version: 2.4
Name: uyghur
Version: 0.1.2
Summary: All things you need for Uyghur Language.
Keywords: Uyghur,NPL
Author: Tang Ziya
Author-email: Tang Ziya <tcztzy@gmail.com>
License-Expression: AGPL-3.0-or-later
Classifier: Development Status :: 3 - Alpha
Classifier: Intended Audience :: Science/Research
Classifier: License :: OSI Approved :: GNU Affero General Public License v3 or later (AGPLv3+)
Classifier: Natural Language :: Chinese (Simplified)
Classifier: Topic :: Text Processing :: Linguistic
Requires-Python: >=3.8
Project-URL: repository, https://github.com/tcztzy/uyghur
